LICENSE.txt
MANIFEST.in
README.rst
REQUIREMENTS.txt
VERSION.txt
setup.cfg
setup.py
craigslist_headless/__init__.py
craigslist_headless/base.py
craigslist_headless/browser.py
craigslist_headless/craigslist.py
craigslist_headless/utils.py
python_craigslist_headless.egg-info/PKG-INFO
python_craigslist_headless.egg-info/SOURCES.txt
python_craigslist_headless.egg-info/dependency_links.txt
python_craigslist_headless.egg-info/requires.txt
python_craigslist_headless.egg-info/top_level.txt