Metadata-Version: 2.1
Name: python-craigslist-headless
Version: 0.0.4
Summary: Simple Craigslist wrapper.
Home-page: https://github.com/f3mshep/python-craigslist-headless
Author: Julio M Alegria, Alexandra Wright
Author-email: superbiscuit@gmail.com
License: MIT-Zero
License-File: LICENSE.txt
